gencbor.py
gencbor-0.1.2.dist-info/LICENSE
gencbor-0.1.2.dist-info/METADATA
gencbor-0.1.2.dist-info/WHEEL
gencbor-0.1.2.dist-info/top_level.txt
gencbor-0.1.2.dist-info/RECORD
