Metadata-Version: 2.1
Name: gencbor
Version: 0.1.2
Summary: A simple generic CBOR encoder / decoder
Home-page: https://github.com/steffen-kiess/gencbor
Author: Steffen Kieß
Author-email: kiess@ki4.de
Project-URL: Bug Tracker, https://github.com/steffen-kiess/gencbor/issues
Classifier: Programming Language :: Python :: 3
Classifier: License :: OSI Approved :: MIT License
Classifier: Operating System :: OS Independent
Requires-Python: >=3.8
License-File: LICENSE
